playwright-1.32.0.dist-info/LICENSE
playwright-1.32.0.dist-info/entry_points.txt
playwright-1.32.0.dist-info/WHEEL
playwright-1.32.0.dist-info/top_level.txt
playwright-1.32.0.dist-info/RECORD
playwright-1.32.0.dist-info/METADATA
playwright/__main__.py
playwright/__init__.py
playwright/_repo_version.py
playwright/py.typed
playwright/_impl/_js_handle.py
playwright/_impl/_connection.py
playwright/_impl/_cdp_session.py
playwright/_impl/_network.py
playwright/_impl/_api_types.py
playwright/_impl/_wait_helper.py
playwright/_impl/_accessibility.py
playwright/_impl/_local_utils.py
playwright/_impl/_async_base.py
playwright/_impl/_har_router.py
playwright/_impl/_selectors.py
playwright/_impl/_impl_to_api_mapping.py
playwright/_impl/_api_structures.py
playwright/_impl/_object_factory.py
playwright/_impl/_stream.py
playwright/_impl/_map.py
playwright/_impl/_event_context_manager.py
playwright/_impl/_assertions.py
playwright/_impl/_tracing.py
playwright/_impl/__init__.py
playwright/_impl/_writable_stream.py
playwright/_impl/_set_input_files_helpers.py
playwright/_impl/_console_message.py
playwright/_impl/_sync_base.py
playwright/_impl/_browser.py
playwright/_impl/_frame.py
playwright/_impl/_locator.py
playwright/_impl/_helper.py
playwright/_impl/_browser_context.py
playwright/_impl/_video.py
playwright/_impl/_dialog.py
playwright/_impl/_str_utils.py
playwright/_impl/_playwright.py
playwright/_impl/_driver.py
playwright/_impl/_input.py
playwright/_impl/_path_utils.py
playwright/_impl/_fetch.py
playwright/_impl/_file_chooser.py
playwright/_impl/_page.py
playwright/_impl/_element_handle.py
playwright/_impl/_transport.py
playwright/_impl/_artifact.py
playwright/_impl/_browser_type.py
playwright/_impl/_download.py
playwright/_impl/_json_pipe.py
playwright/_impl/__pyinstaller/hook-playwright.async_api.py
playwright/_impl/__pyinstaller/__init__.py
playwright/_impl/__pyinstaller/hook-playwright.sync_api.py
playwright/async_api/_context_manager.py
playwright/async_api/__init__.py
playwright/async_api/_generated.py
playwright/sync_api/_context_manager.py
playwright/sync_api/__init__.py
playwright/sync_api/_py37ThreadedChildWatcher.py
