Metadata-Version: 2.1
Name: playwright
Version: 1.32.0
Summary: A high-level API to automate web browsers
Home-page: https://github.com/Microsoft/playwright-python
Author: Microsoft Corporation
Author-email: 
License: Apache-2.0
Project-URL: Release notes, https://github.com/microsoft/playwright-python/releases
Classifier: Topic :: Software Development :: Testing
Classifier: Topic :: Internet :: WWW/HTTP :: Browsers
Classifier: Intended Audience :: Developers
Classifier: Programming Language :: Python :: 3
Classifier: Programming Language :: Python :: 3.7
Classifier: Programming Language :: Python :: 3.8
Classifier: Programming Language :: Python :: 3.9
Classifier: Programming Language :: Python :: 3.10
Classifier: Programming Language :: Python :: 3.11
Classifier: License :: OSI Approved :: Apache Software License
Classifier: Operating System :: OS Independent
Requires-Python: >=3.7
License-File: LICENSE
Requires-Dist: greenlet (==2.0.1)
Requires-Dist: pyee (==9.0.4)
Requires-Dist: typing-extensions ; python_version <= "3.8"
